hkstock_mcp_tools/__init__.py
hkstock_mcp_tools/__main__.py
hkstock_mcp_tools/cli.py
hkstock_mcp_tools/py.typed
hkstock_mcp_tools/core/__init__.py
hkstock_mcp_tools/core/mcp_server.py
hkstock_mcp_tools/database/__init__.py
hkstock_mcp_tools/database/db_manager.py
hkstock_mcp_tools/database/models.py
hkstock_mcp_tools/tools/__init__.py
hkstock_mcp_tools/tools/financial_reports.py
hkstock_mcp_tools/tools/stock_validator.py
hkstock_mcp_tools/tools/yfinance_tools.py
hkstock_mcp_tools/utils/__init__.py
hkstock_mcp_tools-0.1.1.dist-info/licenses/LICENSE
hkstock_mcp_tools-0.1.1.dist-info/METADATA
hkstock_mcp_tools-0.1.1.dist-info/WHEEL
hkstock_mcp_tools-0.1.1.dist-info/entry_points.txt
hkstock_mcp_tools-0.1.1.dist-info/top_level.txt
hkstock_mcp_tools-0.1.1.dist-info/RECORD
