Metadata-Version: 2.4
Name: hkstock-mcp-tools
Version: 0.1.1
Summary: MCP tools for Hong Kong stock data and financial reports
Author-email: Financial Terminal <your-email@example.com>
License: MIT
Project-URL: Homepage, https://github.com/your-username/hkstock-mcp-tools
Project-URL: Repository, https://github.com/your-username/hkstock-mcp-tools
Project-URL: Documentation, https://hkstock-mcp-tools.readthedocs.io
Project-URL: Issues, https://github.com/your-username/hkstock-mcp-tools/issues
Project-URL: Changelog, https://github.com/your-username/hkstock-mcp-tools/blob/main/CHANGELOG.md
Keywords: mcp,hong-kong,stock,financial,akshare,yfinance
Classifier: Development Status :: 3 - Alpha
Classifier: Intended Audience :: Developers
Classifier: License :: OSI Approved :: MIT License
Classifier: Operating System :: OS Independent
Classifier: Programming Language :: Python :: 3
Classifier: Programming Language :: Python :: 3.10
Classifier: Programming Language :: Python :: 3.11
Classifier: Programming Language :: Python :: 3.12
Classifier: Topic :: Office/Business :: Financial
Classifier: Topic :: Software Development :: Libraries :: Python Modules
Requires-Python: >=3.10
License-File: LICENSE
Requires-Dist: mcp>=1.0.0
Requires-Dist: akshare>=1.12.0
Requires-Dist: yfinance>=0.2.0
Requires-Dist: pandas>=1.5.0
Requires-Dist: numpy>=1.20.0
Requires-Dist: duckdb>=0.8.0
Requires-Dist: pydantic>=2.0.0
Requires-Dist: fastapi>=0.100.0
Requires-Dist: uvicorn>=0.23.0
Requires-Dist: python-dateutil>=2.8.0
Provides-Extra: dev
Requires-Dist: pytest>=7.0.0; extra == "dev"
Requires-Dist: pytest-asyncio>=0.21.0; extra == "dev"
Requires-Dist: pytest-cov>=4.0.0; extra == "dev"
Requires-Dist: black>=23.0.0; extra == "dev"
Requires-Dist: isort>=5.12.0; extra == "dev"
Requires-Dist: flake8>=6.0.0; extra == "dev"
Requires-Dist: mypy>=1.0.0; extra == "dev"
Requires-Dist: pre-commit>=3.0.0; extra == "dev"
Provides-Extra: docs
Requires-Dist: sphinx>=5.0.0; extra == "docs"
Requires-Dist: sphinx-rtd-theme>=1.2.0; extra == "docs"
Requires-Dist: myst-parser>=0.18.0; extra == "docs"
Dynamic: license-file
